ships_iiif/__init__.py
ships_iiif/_modidx.py
ships_iiif/api.py
ships_iiif/core.py
ships_iiif/pdf.py
ships_iiif-0.0.1.dist-info/LICENSE
ships_iiif-0.0.1.dist-info/METADATA
ships_iiif-0.0.1.dist-info/WHEEL
ships_iiif-0.0.1.dist-info/entry_points.txt
ships_iiif-0.0.1.dist-info/top_level.txt
ships_iiif-0.0.1.dist-info/RECORD
